chuk_mcp_server/__init__.py
chuk_mcp_server/artifacts_context.py
chuk_mcp_server/cli.py
chuk_mcp_server/context.py
chuk_mcp_server/core.py
chuk_mcp_server/decorators.py
chuk_mcp_server/endpoint_registry.py
chuk_mcp_server/http_server.py
chuk_mcp_server/mcp_registry.py
chuk_mcp_server/protocol.py
chuk_mcp_server/py.typed
chuk_mcp_server/stdio_transport.py
chuk_mcp_server/cloud/__init__.py
chuk_mcp_server/cloud/base.py
chuk_mcp_server/cloud/registry.py
chuk_mcp_server/cloud/adapters/__init__.py
chuk_mcp_server/cloud/adapters/gcf.py
chuk_mcp_server/cloud/providers/__init__.py
chuk_mcp_server/cloud/providers/aws.py
chuk_mcp_server/cloud/providers/azure.py
chuk_mcp_server/cloud/providers/edge.py
chuk_mcp_server/cloud/providers/gcp.py
chuk_mcp_server/composition/__init__.py
chuk_mcp_server/composition/config_loader.py
chuk_mcp_server/composition/manager.py
chuk_mcp_server/config/__init__.py
chuk_mcp_server/config/base.py
chuk_mcp_server/config/cloud_detector.py
chuk_mcp_server/config/container_detector.py
chuk_mcp_server/config/environment_detector.py
chuk_mcp_server/config/network_detector.py
chuk_mcp_server/config/project_detector.py
chuk_mcp_server/config/smart_config.py
chuk_mcp_server/config/system_detector.py
chuk_mcp_server/endpoints/__init__.py
chuk_mcp_server/endpoints/health.py
chuk_mcp_server/endpoints/info.py
chuk_mcp_server/endpoints/mcp.py
chuk_mcp_server/endpoints/ping.py
chuk_mcp_server/endpoints/utils.py
chuk_mcp_server/endpoints/version.py
chuk_mcp_server/middlewares/__init__.py
chuk_mcp_server/middlewares/context_middleware.py
chuk_mcp_server/modules/__init__.py
chuk_mcp_server/modules/loader.py
chuk_mcp_server/oauth/__init__.py
chuk_mcp_server/oauth/base_provider.py
chuk_mcp_server/oauth/base_token_store.py
chuk_mcp_server/oauth/helpers.py
chuk_mcp_server/oauth/middleware.py
chuk_mcp_server/oauth/models.py
chuk_mcp_server/oauth/token_models.py
chuk_mcp_server/oauth/token_store.py
chuk_mcp_server/oauth/providers/__init__.py
chuk_mcp_server-0.15.1.dist-info/licenses/LICENSE
chuk_mcp_server-0.15.1.dist-info/METADATA
chuk_mcp_server-0.15.1.dist-info/WHEEL
chuk_mcp_server-0.15.1.dist-info/entry_points.txt
chuk_mcp_server-0.15.1.dist-info/top_level.txt
chuk_mcp_server-0.15.1.dist-info/RECORD
