Metadata-Version: 2.4
Name: chuk-mcp-server
Version: 0.15.1
Summary: A developer-friendly MCP framework powered by chuk_mcp
License: MIT
Requires-Python: >=3.11
License-File: LICENSE
Requires-Dist: chuk-mcp>=0.8.1
Requires-Dist: chuk-sessions>=0.4.2
Requires-Dist: chuk-tool-processor>=0.11.3
Requires-Dist: httptools>=0.6.4
Requires-Dist: httpx>=0.27.0
Requires-Dist: orjson>=3.10.18
Requires-Dist: psutil>=7.0.0
Requires-Dist: python-multipart>=0.0.6
Requires-Dist: pyyaml>=6.0
Requires-Dist: starlette>=0.47.1
Requires-Dist: uvicorn>=0.35.0
Requires-Dist: uvloop>=0.21.0; sys_platform != "win32"
Provides-Extra: dev
Requires-Dist: pytest>=8.0.0; extra == "dev"
Requires-Dist: pytest-asyncio>=0.24.0; extra == "dev"
Requires-Dist: pytest-cov>=5.0.0; extra == "dev"
Requires-Dist: aiohttp>=3.12.13; extra == "dev"
Requires-Dist: requests>=2.32.4; extra == "dev"
Requires-Dist: ruff>=0.3.0; extra == "dev"
Requires-Dist: mypy>=1.9.0; extra == "dev"
Requires-Dist: pre-commit>=3.6.0; extra == "dev"
Requires-Dist: types-requests>=2.31.0; extra == "dev"
Requires-Dist: types-setuptools>=69.0.0; extra == "dev"
Requires-Dist: types-PyYAML>=6.0.0; extra == "dev"
Requires-Dist: bandit>=1.7.8; extra == "dev"
Provides-Extra: artifacts
Requires-Dist: chuk-artifacts>=0.9; extra == "artifacts"
Requires-Dist: chuk-virtual-fs>=0.3; extra == "artifacts"
Provides-Extra: google-drive
Requires-Dist: google-auth>=2.23.0; extra == "google-drive"
Requires-Dist: google-auth-oauthlib>=1.1.0; extra == "google-drive"
Requires-Dist: google-auth-httplib2>=0.1.1; extra == "google-drive"
Requires-Dist: google-api-python-client>=2.100.0; extra == "google-drive"
Provides-Extra: docs
Requires-Dist: mkdocs>=1.5.0; extra == "docs"
Requires-Dist: mkdocs-material>=9.4.0; extra == "docs"
Requires-Dist: mkdocstrings[python]>=0.24.0; extra == "docs"
Dynamic: license-file
